etc/taemin/conf.yml.orig
taemin/__init__.py
taemin/bot.py
taemin/conf.py
taemin/courriel.py
taemin/database.py
taemin/logger.py
taemin/plugin.py
taemin/profile.py
taemin/schema.py
taemin/sdnotify.py
taemin/__pycache__/__init__.cpython-35.pyc
taemin/_fallback_conf/conf.yml.orig
taemin/plugins/__init__.py
taemin/plugins/airremi/__init__.py
taemin/plugins/airremi/dico.txt
taemin/plugins/airremi/plugin.py
taemin/plugins/akinator/__init__.py
taemin/plugins/akinator/akinator.py
taemin/plugins/akinator/plugin.py
taemin/plugins/ascii/__init__.py
taemin/plugins/ascii/plugin.py
taemin/plugins/bugmenot/__init__.py
taemin/plugins/bugmenot/bugmenot.py
taemin/plugins/bugmenot/plugin.py
taemin/plugins/cafe/__init__.py
taemin/plugins/cafe/plugin.py
taemin/plugins/cine/__init__.py
taemin/plugins/cine/plugin.py
taemin/plugins/compliments/__init__.py
taemin/plugins/compliments/conf.yml
taemin/plugins/compliments/plugin.py
taemin/plugins/dico/__init__.py
taemin/plugins/dico/dico.py
taemin/plugins/dico/dico.txt
taemin/plugins/dico/plugin.py
taemin/plugins/example/__init__.py
taemin/plugins/example/plugin.py
taemin/plugins/images/__init__.py
taemin/plugins/images/image.py
taemin/plugins/images/plugin.py
taemin/plugins/images/schema_image.py
taemin/plugins/images/taemin.conf
taemin/plugins/images/taemin.yml
taemin/plugins/kimsuffi/__init__.py
taemin/plugins/kimsuffi/plugin.py
taemin/plugins/links/__init__.py
taemin/plugins/links/plugin.py
taemin/plugins/loveletter/__init__.py
taemin/plugins/loveletter/loveletter.py
taemin/plugins/loveletter/plugin.py
taemin/plugins/memory/__init__.py
taemin/plugins/memory/plugin.py
taemin/plugins/morpion/__init__.py
taemin/plugins/morpion/morpion.py
taemin/plugins/morpion/plugin.py
taemin/plugins/nicebot/__init__.py
taemin/plugins/nicebot/plugin.py
taemin/plugins/pause/__init__.py
taemin/plugins/pause/plugin.py
taemin/plugins/pendu/__init__.py
taemin/plugins/pendu/dico.txt
taemin-0.1.0.dist-info/DESCRIPTION.rst
taemin-0.1.0.dist-info/METADATA
taemin-0.1.0.dist-info/RECORD
taemin-0.1.0.dist-info/WHEEL
taemin-0.1.0.dist-info/metadata.json
taemin-0.1.0.dist-info/top_level.txt
