Metadata-Version: 2.0
Name: taemin
Version: 0.1.0
Summary: Le plus bot du monde
Home-page: http://github.com/ningirsu/taemin
Author: Sélim Menouar
Author-email: selim.menouar@rez-gif.supelec.fr
License: MIT
Platform: UNKNOWN
Classifier: Programming Language :: Python
Classifier: License :: OSI Approved :: MIT License
Classifier: Topic :: Games/Entertainment
Classifier: Operating System :: OS Independent
Classifier: Programming Language :: Python :: 3 :: Only
Requires-Dist: irc
Requires-Dist: peewee
Requires-Dist: bs4
Requires-Dist: feedparser
Requires-Dist: requests
Requires-Dist: romkan
Requires-Dist: pyyaml
